xDShashank/__init__.py
xDShashank/smex.py
ShashankxD-0.0.2.dist-info/LICENSE
ShashankxD-0.0.2.dist-info/METADATA
ShashankxD-0.0.2.dist-info/WHEEL
ShashankxD-0.0.2.dist-info/top_level.txt
ShashankxD-0.0.2.dist-info/RECORD
