Metadata-Version: 2.1
Name: ShashankxD
Version: 0.0.2
Summary: Shashank xD
Home-page: https://github.com/theshashankk
Author: ShashankxD
Author-email: sharmashashank091@gmail.com
License: UNKNOWN
Platform: UNKNOWN
Classifier: Programming Language :: Python :: 3
Classifier: License :: OSI Approved :: MIT License
Classifier: Operating System :: OS Independent
